LICENSE
MANIFEST.in
README.md
envs.txt
requirements.txt
setup.cfg
setup.py
mp/__init__.py
mp/console.py
mp/debug.py
mp/remote.py
mp/version.py
mp.egg-info/PKG-INFO
mp.egg-info/SOURCES.txt
mp.egg-info/dependency_links.txt
mp.egg-info/not-zip-safe
mp.egg-info/requires.txt
mp.egg-info/top_level.txt
mp/core/__init__.py
mp/core/attribute.py
mp/core/builtins_decorator.py
mp/core/data.py
mp/core/error.py
mp/core/event.py
mp/core/expression.py
mp/core/framework.py
mp/core/graph.py
mp/core/interpreter.py
mp/core/io.py
mp/core/plan.py
mp/core/token.py
mp/core/builtins/__init__.py
mp/core/builtins/core.py
mp/core/builtins/trace.py
mp/dataset/__init__.py
mp/dataset/core.py
mp/dataset/mnist.py
mp/engine/__init__.py
mp/engine/pytorch/__init__.py
mp/engine/pytorch/device.py
mp/engine/pytorch/framework.py
mp/engine/pytorch/interpreter.py
mp/engine/pytorch/io.py
mp/engine/pytorch/plan.py
mp/engine/pytorch/builtins/__init__.py
mp/engine/pytorch/builtins/builtins.mp
mp/engine/pytorch/builtins/core.py
mp/engine/pytorch/builtins/dataset.py
mp/engine/pytorch/builtins/math.py
mp/engine/pytorch/builtins/nn.py
mp/engine/pytorch/builtins/optim.py
mp/engine/pytorch/builtins/reduce.py
mp/engine/remote/__init__.py
mp/engine/remote/interpreter.py
mp/markdown/__init__.py
mp/markdown/base.py
mp/markdown/graph.py
mp/markdown/script.py
mp/monitor/__init__.py
mp/monitor/std.py
mp/trainer/__init__.py
mp/trainer/supervised.py
mp/utils/__init__.py
mp/utils/console.py
mp/utils/dependency.py
mp/utils/environment.py
mp/utils/filename.py
mp/utils/find_interpreter.py