Metadata-Version: 2.1
Name: mp
Version: 0.4.2.5
Summary: Machine Pseudo-Code
Home-page: https://github.com/kerryeon/mp
Author: kerryeon
Author-email: besqer996@gnu.ac.kr
License: MIT
Platform: any
Classifier: Programming Language :: Python :: 3
Classifier: Programming Language :: Python :: 3.6
Classifier: Programming Language :: Python :: 3.7
